{
  "seed": 42,
  "budget": 260,
  "init_n": 95,
  "batch_size": 20,
  "pool_size": 14000,
  "output_dir": "outputs",
  "run_id": null,
  "output_csv": "comp_car_quotes_advanced.csv",
  "output_metadata_json": "run_metadata.json",
  "state_path": "run_state.json",
  "engine_path": "pricing_engine.pkl",
  "resume": false,
  "checkpoint_every_batches": 1,
  "refit_every_batches": 1,
  "cv_subsample_max": 1200,
  "use_monotone_if_available": true,
  "distance_backend": "knn",
  "acquisition_mix": [0.45, 0.25, 0.20, 0.10],
  "breakpoint_vars": [
    "driver_age",
    "postcode_risk",
    "vehicle_value",
    "excess",
    "vehicle_year",
    "annual_km"
  ],
  "rf_n_models": 20,
  "rf_n_estimators": 600,
  "rf_n_jobs": -1,
  "quote_provider": null,
  "domain_overrides": {
    "continuous": {},
    "integers": {},
    "categorical": {}
  }
}
